jolt/__init__.py
jolt/client.py
jolt/config.py
jolt/exceptions.py
jolt/handler.py
jolt/request.py
jolt/response.py
jolt_python_api-2.4.3.dist-info/licenses/LICENSE
jolt_python_api-2.4.3.dist-info/METADATA
jolt_python_api-2.4.3.dist-info/WHEEL
jolt_python_api-2.4.3.dist-info/top_level.txt
jolt_python_api-2.4.3.dist-info/RECORD
